odd_ml/__init__.py
odd_ml/client.py
odd_ml/dataset_storage/__init__.py
odd_ml/dataset_storage/dataset_storage.py
odd_ml/dataset_storage/s3_storage.py
odd_ml/domain/__init__.py
odd_ml/domain/aws_config.py
odd_ml/domain/data_entities.py
odd_ml/domain/data_entity.py
odd_ml/domain/data_source.py
odd_ml/domain/namespace.py
odd_ml/errors.py
odd_ml/helpers/__init__.py
odd_ml/helpers/asci_renderer.py
odd_ml/helpers/get_s3_path.py
odd_ml/helpers/oddrn_to_s3_path.py
odd_ml/http/__init__.py
odd_ml/http/http_client.py
odd_ml/profiler/__init__.py
odd_ml/profiler/pandas_profiler.py
odd_ml/profiler/profiler.py
odd_ml/renderer.py
odd_ml/utils/__init__.py
odd_ml/utils/datetime_to_str.py
odd_ml/utils/log.py
odd_ml-0.6.1.dist-info/LICENSE
odd_ml-0.6.1.dist-info/WHEEL
odd_ml-0.6.1.dist-info/METADATA
odd_ml-0.6.1.dist-info/RECORD
